Metadata-Version: 2.4
Name: pubpypack-harmony-weiwen-chen
Version: 0.0.1
Summary: This package does amazing things.
Home-page: https://github.com/weiwenchen2022/first-python-package
Author: weiwenchen
Author-email: "weiwenchen2022@163.com"
License: MIT
Classifier: License :: OSI Approved :: MIT License
Requires-Python: >=3.9
License-File: LICENSE
Requires-Dist: termcolor<4,>=3.1.0
Dynamic: license-file
